uvicorn_http2/__init__.py
uvicorn_http2/py.typed
uvicorn_http2-0.0.0.dist-info/METADATA
uvicorn_http2-0.0.0.dist-info/WHEEL
uvicorn_http2-0.0.0.dist-info/RECORD
