Metadata-Version: 2.1
Name: uvicorn-http2
Version: 0.0.0
Summary: Uvicorn with HTTP/2 support! :rocket:
Author-email: Marcelo Trylesinski <marcelotryle@gmail.com>
License: MIT
